lean_dojo/__init__.py
lean_dojo/constants.py
lean_dojo/utils.py
lean_dojo/data_extraction/ExtractData.lean
lean_dojo/data_extraction/ast.py
lean_dojo/data_extraction/cache.py
lean_dojo/data_extraction/lean.py
lean_dojo/data_extraction/trace.py
lean_dojo/data_extraction/traced_data.py
lean_dojo/interaction/Lean4Repl.lean
lean_dojo/interaction/dojo.py
lean_dojo/interaction/parse_goals.py
lean_dojo-2.2.0.dist-info/METADATA
lean_dojo-2.2.0.dist-info/WHEEL
lean_dojo-2.2.0.dist-info/licenses/LICENSE
lean_dojo-2.2.0.dist-info/RECORD
