Metadata-Version: 2.4
Name: lean-dojo
Version: 2.2.0
Summary: LeanDojo: Machine Learning for Theorem Proving in Lean
Project-URL: Homepage, https://leandojo.org/
Project-URL: Bug Tracker, https://github.com/lean-dojo/LeanDojo/issues
Author-email: Kaiyu Yang <kaiyuy@meta.com>
License: MIT License
License-File: LICENSE
Keywords: Lean,machine learning,theorem proving
Classifier: License :: OSI Approved :: MIT License
Classifier: Operating System :: MacOS
Classifier: Operating System :: POSIX :: Linux
Classifier: Programming Language :: Python :: 3
Requires-Python: <=3.12,>=3.9
Requires-Dist: filelock
Requires-Dist: gitpython
Requires-Dist: loguru
Requires-Dist: lxml
Requires-Dist: networkx
Requires-Dist: pexpect
Requires-Dist: psutil
Requires-Dist: pygithub
Requires-Dist: python-dotenv
Requires-Dist: ray[default]>=2.8
Requires-Dist: toml
Requires-Dist: tqdm
Requires-Dist: types-psutil
Requires-Dist: types-toml
Provides-Extra: all
Requires-Dist: black[jupyter]; extra == 'all'
Requires-Dist: hatch; extra == 'all'
Requires-Dist: ipython; extra == 'all'
Requires-Dist: mypy; extra == 'all'
Requires-Dist: notebook; extra == 'all'
Requires-Dist: pytest; extra == 'all'
Requires-Dist: sphinx; extra == 'all'
Requires-Dist: sphinx-rtd-theme; extra == 'all'
Provides-Extra: dev
Requires-Dist: hatch; extra == 'dev'
Requires-Dist: ipython; extra == 'dev'
Requires-Dist: notebook; extra == 'dev'
Provides-Extra: docs
Requires-Dist: sphinx; extra == 'docs'
Requires-Dist: sphinx-rtd-theme; extra == 'docs'
Provides-Extra: lint
Requires-Dist: black[jupyter]; extra == 'lint'
Requires-Dist: mypy; extra == 'lint'
Provides-Extra: test
Requires-Dist: pytest; extra == 'test'
